pandera_alchemy/__init__.py
pandera_alchemy/exceptions.py
pandera_alchemy/logger.py
pandera_alchemy/table.py
pandera_alchemy/unified_types.py
pandera_alchemy-1.1.0.dist-info/LICENSE
pandera_alchemy-1.1.0.dist-info/METADATA
pandera_alchemy-1.1.0.dist-info/WHEEL
pandera_alchemy-1.1.0.dist-info/RECORD
