Metadata-Version: 2.1
Name: pandera-alchemy
Version: 1.1.0
Summary: A package that enables using Pandera DataFrame Models to validate SQL Alchemy table schemas
Author: Thomas Richards
Author-email: thomas.c.richards@outlook.com
Requires-Python: >=3.9,<4.0
Classifier: Programming Language :: Python :: 3
Classifier: Programming Language :: Python :: 3.9
Classifier: Programming Language :: Python :: 3.10
Classifier: Programming Language :: Python :: 3.11
Classifier: Programming Language :: Python :: 3.12
Requires-Dist: numpy (>=1.23,<2.0)
Requires-Dist: pandas (>=1.5,<2.0)
Requires-Dist: pandera (>=0.20.3,<0.21.0)
Requires-Dist: sqlalchemy (>=1.4,<2.0)
